irccodes/__init__.py
irccodes/constants.py
irccodes/symbols.py
irccodes-1.2.0.dist-info/METADATA
irccodes-1.2.0.dist-info/WHEEL
irccodes-1.2.0.dist-info/top_level.txt
irccodes-1.2.0.dist-info/RECORD
