Metadata-Version: 2.1
Name: irccodes
Version: 1.2.0
Summary: Python module for formatting text in IRC
Home-page: https://github.com/TomasGlgg/irccodes
Author: Tomas Globis
License: UNKNOWN
Platform: UNKNOWN
Classifier: Programming Language :: Python :: 3
Classifier: Development Status :: 6 - Mature
Classifier: Intended Audience :: Developers
Classifier: Topic :: Communications :: Chat :: Internet Relay Chat
Classifier: Topic :: Software Development :: Libraries :: Python Modules
Classifier: Topic :: Text Processing :: Filters
